{
  "asin_groups": 3,
  "asin_list_1": ["B08MVC76SR"],
  "reserve_min_1": 600,
  "reserve_max_1": 800,
  "asin_list_2": ["B08NX14LV1"],
  "reserve_min_2": 600,
  "reserve_max_2": 800,
  "asin_list_3": ["B08P3ZN62G"],
  "reserve_min_3": 600,
  "reserve_max_3": 800,
  "asin_list_4": ["B08NS4W2ZY"],
  "reserve_min_4": 600,
  "reserve_max_4": 800,
  "asin_list_5": ["B08N6ZLX9B"],
  "reserve_min_5": 600,
  "reserve_max_5": 800,
  "asin_list_6": ["B08NXXT7WN"],
  "reserve_min_6": 600,
  "reserve_max_6": 800,
  "asin_list_7": ["B08NXYNLMR"],
  "reserve_min_7": 600,
  "reserve_max_7": 800,
  "asin_list_8": ["B08MVC76SR"],
  "reserve_min_8": 600,
  "reserve_max_8": 800,
  "asin_list_9": ["B08P2BQRLW"],
  "reserve_min_9": 600,
  "reserve_max_9": 800,
  "asin_list_10": ["B08HH5WF97"],
  "reserve_min_10": 500,
  "reserve_max_10": 800,
  "asin_list_11": ["B08HHDP9DW"],
  "reserve_min_11": 500,
  "reserve_max_11": 800,
  "asin_list_12": ["B08HBR7QBM"],
  "reserve_min_12": 500,
  "reserve_max_12": 800,
  "asin_list_13": ["B08HBTJMLJ"],
  "reserve_min_13": 500,
  "reserve_max_13": 800,
  "asin_list_14": ["B08HR5SXPS"],
  "reserve_min_14": 500,
  "reserve_max_14": 800,
  "asin_list_15": ["B08HR7SV3M"],
  "reserve_min_15": 500,
  "reserve_max_15": 800,
  "asin_list_16": ["B08HR3Y5GQ"],
  "reserve_min_16": 500,
  "reserve_max_16": 800,
  "asin_list_17": ["B08HR3DPGW"],
  "reserve_min_17": 500,
  "reserve_max_17": 800,
  "asin_list_18": ["B08HR55YB5"],
  "reserve_min_18": 500,
  "reserve_max_18": 800,
  "asin_list_19": ["B08HR4RJ3Q"],
  "reserve_min_19": 500,
  "reserve_max_19": 800,
  "asin_list_20": ["B08HR6FMF3"],
  "reserve_min_20": 500,
  "reserve_max_20": 800,
  "amazon_website": "smile.amazon.com"
}
